fortext/__init__.py
fortext/ansi.py
fortext/constants.py
fortext/permutation.py
fortext/py.typed
fortext/style.py
fortext/syntax.py
fortext-1.1.2.dist-info/METADATA
fortext-1.1.2.dist-info/WHEEL
fortext-1.1.2.dist-info/licenses/LICENSE
fortext-1.1.2.dist-info/RECORD
